README.md
setup.py
folktales/__init__.py
folktales.egg-info/PKG-INFO
folktales.egg-info/SOURCES.txt
folktales.egg-info/dependency_links.txt
folktales.egg-info/not-zip-safe
folktales.egg-info/requires.txt
folktales.egg-info/top_level.txt