Metadata-Version: 1.0
Name: folktales
Version: 2018.5.3.245
Summary: creation, access and modification of SQL databases
Home-page: https://github.com/wdbm/folktales
Author: Will Breaden Madden
Author-email: wbm@protonmail.ch
License: GPLv3
Platform: UNKNOWN
